cafe/__init__.py
cafe_ai-0.0.1.dist-info/licenses/LICENSE
cafe_ai-0.0.1.dist-info/METADATA
cafe_ai-0.0.1.dist-info/WHEEL
cafe_ai-0.0.1.dist-info/top_level.txt
cafe_ai-0.0.1.dist-info/RECORD
